nshap/InteractionIndex.py
nshap/__init__.py
nshap/functions.py
nshap/plot.py
nshap/util.py
nshap/vfunc.py
nshap-0.2.0.dist-info/LICENSE
nshap-0.2.0.dist-info/METADATA
nshap-0.2.0.dist-info/WHEEL
nshap-0.2.0.dist-info/top_level.txt
nshap-0.2.0.dist-info/RECORD
