Metadata-Version: 2.1
Name: nshap
Version: 0.2.0
Summary: Python package to compute n-Shapley Values.
Home-page: https://github.com/tml-tuebingen/nshap
Author: Sebastian Bordt
Author-email: sbordt@posteo.de
Classifier: Programming Language :: Python :: 3
Classifier: License :: OSI Approved :: MIT License
Classifier: Operating System :: OS Independent
Requires-Python: >=3.6
License-File: LICENSE
Requires-Dist: numpy
Requires-Dist: matplotlib
Requires-Dist: seaborn
